bodybuilder/__init__.py
bodybuilder/builder.py
tests/__init__.py
tests/test_builder.py
venv/__init__.py
venv/lib/__init__.py
bodybuilder-0.1.0.dist-info/LICENSE
bodybuilder-0.1.0.dist-info/METADATA
bodybuilder-0.1.0.dist-info/WHEEL
bodybuilder-0.1.0.dist-info/top_level.txt
bodybuilder-0.1.0.dist-info/RECORD
