Metadata-Version: 2.1
Name: bodybuilder
Version: 0.1.0
Summary: A python port of the NPM Bodybuilder Package
Home-page: https://github.com/alexsanjoseph/bodybuilder
Author: Alex Joseph
Author-email: alexsanjoseph@gmail.com
License: UNKNOWN
Platform: UNKNOWN
Classifier: Programming Language :: Python :: 3
Classifier: License :: OSI Approved :: MIT License
Classifier: Operating System :: OS Independent
Requires-Python: >=3.6
